botter/__init__.py
botter/api/__init__.py
botter/api/bot.py
botter/api/bot_api.py
botter/api/bot_base.py
botter/api/bot_impl.py
botter/api/errors.py
botter/api/handlers/__init__.py
botter/api/handlers/command_handler.py
botter/api/handlers/event_aggregator.py
botter/api/handlers/event_handler.py
botter/api/handlers/message_handler.py
botter/api/handlers/start_handler.py
botter/discord/__init__.py
botter/discord/discord_api.py
botter/discord/discord_bot.py
botter/telegram/__init__.py
botter/telegram/telegram_api.py
botter/telegram/telegram_bot.py
botter/util/__init__.py
botter/util/backport.py
botter/util/docs.py
botter/util/logging.py
botter/util/os_operations.py
botter-0.1.4.dist-info/LICENSE
botter-0.1.4.dist-info/METADATA
botter-0.1.4.dist-info/WHEEL
botter-0.1.4.dist-info/top_level.txt
botter-0.1.4.dist-info/RECORD
