Metadata-Version: 2.1
Name: botter
Version: 0.1.4
Summary: Python messenger bot aggregator, supporting Discord, Telegram, and potentially others
Home-page: https://gitlab.com/Hares-Lab/botter/botter-core
License: BSD 2-Clause License
Platform: UNKNOWN
Classifier: Development Status :: 2 - Pre-Alpha
Classifier: License :: OSI Approved :: BSD License
Classifier: Intended Audience :: Developers
Classifier: Natural Language :: English
Classifier: Operating System :: OS Independent
Classifier: Programming Language :: Python :: 3.6
Classifier: Programming Language :: Python :: 3.7
Classifier: Topic :: Internet
Classifier: Topic :: Communications
Classifier: Topic :: Communications :: Chat
Classifier: Topic :: Software Development :: Libraries
Classifier: Topic :: Software Development :: Libraries :: Python Modules
Classifier: Topic :: Utilities
Requires-Python: >=3.6.0
Requires-Dist: dataclasses-json (>=0.2.13)
Requires-Dist: dataclasses (>=0.6) ; python_version < "3.7"
Provides-Extra: discord
Requires-Dist: discord.py (>=1.3.4) ; extra == 'discord'
Provides-Extra: telegram
Requires-Dist: python-telegram-bot (>=12.0.0b1) ; extra == 'telegram'
Requires-Dist: functional-python (>=0.0.1) ; extra == 'telegram'
Provides-Extra: all
Requires-Dist: discord.py (>=1.3.4) ; extra == 'all'
Requires-Dist: python-telegram-bot (>=12.0.0b1) ; extra == 'all'
Requires-Dist: functional-python (>=0.0.1) ; extra == 'all'
